GenBioX/__init__.py
GenBioX/alignment/__init__.py
GenBioX/alignment/align.py
GenBioX/alignment/evaluate_alignment_quality.py
GenBioX/alignment/extract_conserved_regions.py
GenBioX/alignment/merge_alignments.py
GenBioX/alignment/read_alignment.py
GenBioX/annotation/__init__.py
GenBioX/annotation/annotation.py
GenBioX/annotation/ap_qualityCheck.py
GenBioX/annotation/extract_annotations.py
GenBioX/annotation/filter_annotations.py
GenBioX/annotation/search_annotations.py
GenBioX/annotation/test_annotation.py
GenBioX/annotation/test_annotation_processing.py
GenBioX/comparative_genomics/__init__.py
GenBioX/comparative_genomics/compare_genome_size.py
GenBioX/comparative_genomics/conserved_regions.py
GenBioX/comparative_genomics/identify_conserved_regions.py
GenBioX/comparative_genomics/pairwise_identity.py
GenBioX/comparative_genomics/phylogenetic_distance.py
GenBioX/data_preprocessing/__init__.py
GenBioX/data_preprocessing/extract_annotation.py
GenBioX/data_preprocessing/fasta.py
GenBioX/data_preprocessing/fasta_quality_check.py
GenBioX/data_preprocessing/fetch_seq.py
GenBioX/data_preprocessing/filter_contaminants.py
GenBioX/data_preprocessing/filter_low_quality_read.py
GenBioX/data_preprocessing/quality_score.py
GenBioX/data_preprocessing/read_fasta.py
GenBioX/data_preprocessing/remove_duplicates.py
GenBioX/data_preprocessing/test2.py
GenBioX/data_preprocessing/test_fetch_seq.py
GenBioX/data_preprocessing/test_read_fasta.py
GenBioX/data_preprocessing/trim_adapters.py
GenBioX/data_preprocessing/vcf.py
GenBioX/data_preprocessing/visualise_quality_metrics.py
GenBioX/gene_expression/__init__.py
GenBioX/gene_expression/diff_gene_exp.py
GenBioX/gene_expression/differential_gene_expression_analysis.py
GenBioX/gene_expression/gene_expression_correlation.py
GenBioX/gene_expression/gene_expression_normaization.py
GenBioX/gene_expression/gene_expression_normalization.py
GenBioX/gene_expression/gene_expression_quantification.py
GenBioX/statistical_analysis/__init__.py
GenBioX-0.2.dist-info/METADATA
GenBioX-0.2.dist-info/WHEEL
GenBioX-0.2.dist-info/top_level.txt
GenBioX-0.2.dist-info/RECORD
