Metadata-Version: 2.1
Name: GenBioX
Version: 0.2
Summary: A package for Genome Analysis
Home-page: https://github.com/SayaGarud/GenBioX.git
Author: Sayali Garud
Author-email: sayaligrud@gmail.com
License: MIT
Classifier: Development Status :: 3 - Alpha
Classifier: License :: OSI Approved :: MIT License
Classifier: Programming Language :: Python :: 3
Classifier: Programming Language :: Python :: 3.6
Classifier: Programming Language :: Python :: 3.7
Classifier: Programming Language :: Python :: 3.8
Classifier: Programming Language :: Python :: 3.9
Classifier: Intended Audience :: Science/Research
Classifier: Topic :: Scientific/Engineering :: Bio-Informatics
Requires-Dist: pandas (>=1.3.0)
Requires-Dist: numpy (>=1.21.1)
Requires-Dist: Biopython (>=1.79)
Requires-Dist: scikit-allel (>=1.3.2)
